fbemissary/__init__.py
fbemissary/client.py
fbemissary/conversation.py
fbemissary/core.py
fbemissary/models.py
fbemissary/webhook.py
fbemissary/tests/__init__.py
fbemissary/tests/test_models.py
fbemissary-0.0.2.dist-info/DESCRIPTION.rst
fbemissary-0.0.2.dist-info/METADATA
fbemissary-0.0.2.dist-info/RECORD
fbemissary-0.0.2.dist-info/WHEEL
fbemissary-0.0.2.dist-info/metadata.json
fbemissary-0.0.2.dist-info/top_level.txt
