Metadata-Version: 2.0
Name: fbemissary
Version: 0.0.2
Summary: A bot framework for the Facebook Messenger platform, built on asyncio and aiohttp
Home-page: https://github.com/cdunklau/fbemissary
Author: Colin Dunklau
Author-email: colin.dunklau@gmail.com
License: UNKNOWN
Platform: UNKNOWN
Classifier: Programming Language :: Python :: 3.5
Classifier: Programming Language :: Python :: 3.6
Classifier: Programming Language :: Python :: 3 :: Only
Classifier: Framework :: AsyncIO
Classifier: Topic :: Internet
Classifier: Topic :: Communications :: Chat
Classifier: License :: OSI Approved :: Apache Software License
Classifier: Development Status :: 2 - Pre-Alpha
Requires-Dist: aiohttp
Requires-Dist: attrs
